testkczajkowska/__init__.py
testkczajkowska/m_mod_kczajkowska.py
testkczajkowska-0.0.4.dist-info/LICENSE.txt
testkczajkowska-0.0.4.dist-info/METADATA
testkczajkowska-0.0.4.dist-info/WHEEL
testkczajkowska-0.0.4.dist-info/top_level.txt
testkczajkowska-0.0.4.dist-info/RECORD
