Metadata-Version: 2.1
Name: testkczajkowska
Version: 0.0.4
Summary: My test package
Author-email: KC <czajkowska.kamila@wp.pl>
License: MIT License
Keywords: testkczajkowska,name,surname,age
Classifier: Framework :: IDLE
Classifier: Framework :: Opps
Requires-Python: >=3.0
License-File: LICENSE.txt
Requires-Dist: python-version (>='3.0')
Requires-Dist: numpy
